LICENSE
MANIFEST.in
README.md
VERSION.txt
requirements.txt
setup.cfg
setup.py
ckanext/__init__.py
ckanext/file_uploader_ui/__init__.py
ckanext/file_uploader_ui/plugin.py
ckanext/file_uploader_ui/fanstatic/base.js
ckanext/file_uploader_ui/fanstatic/blueimp-gallery.css
ckanext/file_uploader_ui/fanstatic/canvas-to-blob.js
ckanext/file_uploader_ui/fanstatic/jquery.blueimp-gallery.js
ckanext/file_uploader_ui/fanstatic/jquery.fileupload-audio.js
ckanext/file_uploader_ui/fanstatic/jquery.fileupload-image.js
ckanext/file_uploader_ui/fanstatic/jquery.fileupload-jquery-ui.js
ckanext/file_uploader_ui/fanstatic/jquery.fileupload-process.js
ckanext/file_uploader_ui/fanstatic/jquery.fileupload-ui.css
ckanext/file_uploader_ui/fanstatic/jquery.fileupload-ui.js
ckanext/file_uploader_ui/fanstatic/jquery.fileupload-validate.js
ckanext/file_uploader_ui/fanstatic/jquery.fileupload-video.js
ckanext/file_uploader_ui/fanstatic/jquery.fileupload.css
ckanext/file_uploader_ui/fanstatic/jquery.fileupload.js
ckanext/file_uploader_ui/fanstatic/jquery.iframe-transport.js
ckanext/file_uploader_ui/fanstatic/jquery.ui.widget.js
ckanext/file_uploader_ui/fanstatic/load-image-exif-map.js
ckanext/file_uploader_ui/fanstatic/load-image-exif.js
ckanext/file_uploader_ui/fanstatic/load-image-fetch.js
ckanext/file_uploader_ui/fanstatic/load-image-meta.js
ckanext/file_uploader_ui/fanstatic/load-image-orientation.js
ckanext/file_uploader_ui/fanstatic/load-image-scale.js
ckanext/file_uploader_ui/fanstatic/load-image.js
ckanext/file_uploader_ui/fanstatic/main.js
ckanext/file_uploader_ui/fanstatic/resource.config
ckanext/file_uploader_ui/fanstatic/tmpl.js
ckanext/file_uploader_ui/fanstatic/img/loading.gif
ckanext/file_uploader_ui/fanstatic/img/progressbar.gif
ckanext/file_uploader_ui/i18n/ar/LC_MESSAGES/ckanext-file_uploader_ui.mo
ckanext/file_uploader_ui/i18n/he/LC_MESSAGES/ckanext-file_uploader_ui.mo
ckanext/file_uploader_ui/templates/ckanext-file_uploader_ui/upload.html
ckanext_file_uploader_ui.egg-info/PKG-INFO
ckanext_file_uploader_ui.egg-info/SOURCES.txt
ckanext_file_uploader_ui.egg-info/dependency_links.txt
ckanext_file_uploader_ui.egg-info/entry_points.txt
ckanext_file_uploader_ui.egg-info/namespace_packages.txt
ckanext_file_uploader_ui.egg-info/top_level.txt