Metadata-Version: 1.1
Name: ckanext-file-uploader-ui
Version: 0.1.4
Summary: Enhance file uploader UI for CKAN
Home-page: https://github.com/OriHoch/ckanext-file_uploader_ui
Author: Ori Hoch
Author-email: ori@uumpa.com
License: AGPL
Keywords: CKAN file upload
Platform: UNKNOWN
Classifier: Development Status :: 4 - Beta
Classifier: License :: OSI Approved :: GNU Affero General Public License v3 or later (AGPLv3+)
Classifier: Programming Language :: Python :: 2.7
